jenga/__init__.py
jenga/basis.py
jenga/utils.py
jenga/corruptions/generic.py
jenga/corruptions/image.py
jenga/corruptions/numerical.py
jenga/corruptions/text.py
jenga/evaluation/basis.py
jenga/evaluation/corruption_impact.py
jenga/evaluation/schema_stresstest.py
jenga/evaluation/schema_validation.py
jenga/tasks/income.py
jenga/tasks/openml.py
jenga/tasks/reviews.py
jenga/tasks/shoes.py
jenga-0.0.1a1.dist-info/AUTHORS.rst
jenga-0.0.1a1.dist-info/LICENSE.txt
jenga-0.0.1a1.dist-info/METADATA
jenga-0.0.1a1.dist-info/WHEEL
jenga-0.0.1a1.dist-info/top_level.txt
jenga-0.0.1a1.dist-info/RECORD
