Metadata-Version: 2.1
Name: jenga
Version: 0.0.1a1
Summary: Jenga is an open source experimentation library that allows data science practititioners and researchers to study the effect of common data corruptions (e.g., missing values, broken character encodings) on the prediction quality of their ML models.
Home-page: https://github.com/schelterlabs/jenga
Author: Sebastian Schelter
Author-email: s.schelter@uva.nl
License: gpl3
Project-URL: Documentation, https://github.com/schelterlabs/jenga
Platform: any
Classifier: Development Status :: 4 - Beta
Classifier: Programming Language :: Python
Requires-Python: <3.10.*,>=3.7.*
License-File: LICENSE.txt
License-File: AUTHORS.rst
Requires-Dist: scikit-learn
Requires-Dist: pandas
Provides-Extra: all
Requires-Dist: imgaug ; extra == 'all'
Requires-Dist: imagecorruptions ; extra == 'all'
Requires-Dist: tensorflow ; extra == 'all'
Requires-Dist: tensorflow-data-validation ; extra == 'all'
Provides-Extra: image
Requires-Dist: imgaug ; extra == 'image'
Requires-Dist: tensorflow ; extra == 'image'
Requires-Dist: imagecorruptions ; extra == 'image'
Provides-Extra: testing
Requires-Dist: pytest ; extra == 'testing'
Requires-Dist: pytest-cov ; extra == 'testing'
Provides-Extra: validation
Requires-Dist: tensorflow ; extra == 'validation'
Requires-Dist: tensorflow-data-validation ; extra == 'validation'
